permission_graph-0.1.0a1.dist-info/METADATA
permission_graph-0.1.0a1.dist-info/WHEEL
permission_graph/__init__.py
permission_graph/backends/__init__.py
permission_graph/backends/base.py
permission_graph/backends/igraph.py
permission_graph/permission_graph.py
permission_graph/structs.py
permission_graph-0.1.0a1.dist-info/RECORD
