Metadata-Version: 2.1
Name: permission-graph
Version: 0.1.0a1
Summary: A graph based authorization library
Author-Email: Grayden Shand <graydenshand@gmail.com>
License: MIT
Requires-Python: >=3.11
Requires-Dist: igraph>=0.10.8
